Instaweb/__init__.py
Instaweb/client.py
instaweb-1.4.dist-info/licenses/LICENSE
instaweb-1.4.dist-info/METADATA
instaweb-1.4.dist-info/WHEEL
instaweb-1.4.dist-info/entry_points.txt
instaweb-1.4.dist-info/top_level.txt
instaweb-1.4.dist-info/RECORD
